[
    {
        "lineNo": 1,
        "lineEn": "Narrator: Hello, it's a chilly start to the day at Tip Top Trading.",
        "linePl": "Narrator: Witam, to jest chłodny początek dnia w Tip Top Trading.\r",
        "mp3Start": "4.3",
        "mp3End": "8"
    },
    {
        "lineNo": 2,
        "lineEn": "Anna:  Hi Denise!",
        "linePl": "Anna: Cześć Denise!\r",
        "mp3Start": "9.5",
        "mp3End": "10.5"
    },
    {
        "lineNo": 3,
        "lineEn": "Denise:  Good morning Anna.",
        "linePl": "Denise: Dzień dobry Anna.\r",
        "mp3Start": "10.5",
        "mp3End": "12.3"
    },
    {
        "lineNo": 4,
        "lineEn": "Anna:  Brrr... it's so cold in here.",
        "linePl": "Anna: Brrr ... tu jest tak zimno.\r",
        "mp3Start": "12.5",
        "mp3End": "14.9"
    },
    {
        "lineNo": 5,
        "lineEn": "Denise: The window was left open overnight.",
        "linePl": "Denise: Okno było otwarte przez noc.\r",
        "mp3Start": "15.1",
        "mp3End": "17.7"
    },
    {
        "lineNo": 6,
        "lineEn": "Anna:  My papers have been blown everywhere.",
        "linePl": "Anna: Moje dokumenty zostały rozdmuchiwane wszędzie.\r",
        "mp3Start": "17.7",
        "mp3End": "20.0"
    },
    {
        "lineNo": 7,
        "lineEn": "Denise: Mine too! Tom was the last one here last night – it must've been him who left the window open.",
        "linePl": "Denise: też moje! Tom był ostatnim tutaj wczoraj - musiał to być on, kto zostawił okno.\r",
        "mp3Start": "20.2",
        "mp3End": "26.5"
    },
    {
        "lineNo": 8,
        "lineEn": "Anna:  Brrr.... Right then, to work! Oh, there's a note from Paul, it must've fallen off my desk: ",
        "linePl": "Anna: Brrr ... Zaraz, żeby pracować! Och, jest notatka Paula, musiało to spaść z mojego biurka:  \n",
        "mp3Start": "26.8",
        "mp3End": "34.3"
    },
    {
        "linePl": "\"Chciałbym twoich pomysłów na nasz system zarządzania zapasami w zakresie naszym nowym owoców lasera krzywej, żebyśmy wiedzieli, że możemy nadążyć za zamówieniami.",
        "lineEn": "'I would like your ideas on our stock management system for our new laser-curve fruit range, so we know we can keep up with demand. ",
        "lineNo": 9,
        "mp3Start": "34.3",
        "mp3End": "44.4"
    },
    {
        "linePl": "Proszę napisz do mnie parę stron sugestii i zostaw ją na biurku. Wrócę dziś po południu. ",
        "lineEn": "Please write me a couple of pages of suggestions and leave it on my desk. I'll be back this afternoon.' ",
        "lineNo": 10,
        "mp3Start": "44.4",
        "mp3End": "52.0"
    },
    {
        "linePl": "Łał! Muszę wymyślić pomysły na system zarządzania zapasami! Gosh, gdzie zacznę ?!",
        "lineEn": "Wow! I have to come up with ideas for a stock management system! Gosh, where do I begin?!",
        "lineNo": 11,
        "mp3Start": "52.5",
        "mp3End": "59.6"
    },
    {
        "lineNo": 12,
        "lineEn": "Tom:  Good morning. Anna:  Morning!",
        "linePl": "Tom: Dzień dobry.\r Anna: Rano!\r",
        "mp3Start": "62.5",
        "mp3End": "64.7"
    },
    {
        "lineNo": 13,
        "lineEn": "Tom:  Hey, my certificate for Plastic Pear Salesman of the Year is on the floor!",
        "linePl": "Tom: Hej, mój certyfikat za plastik Gruszka sprzedawca roku jest na podłodze!\r",
        "mp3Start": "64.7",
        "mp3End": "70"
    },
    {
        "lineNo": 14,
        "lineEn": "Anna: Right... stock management systems... stock-up on your laser-curved lemons … My first idea is to calculate the total…. ",
        "linePl": "Anna: Właściwe ... systemy zarządzania zapasami ... zapas na cytrynach zakrzywionych laserem ... Moja pierwsza idea to obliczyć całkowitą ilość ....\r",
        "mp3Start": "70.3",
        "mp3End": "81.6"
    },
    {
        "lineNo": 15,
        "lineEn": "Narrator: Well, Anna has finished her report and left it on Paul's desk, but things  aren't that simple. Er, Anna, there's going to be a problem.",
        "linePl": "Narrator: Cóż, Anna skończyła sprawozdanie i zostawiła ją na biurku Paula, ale rzeczy nie są takie proste. Er, Anna, będzie problem.\n",
        "mp3Start": "85.5",
        "mp3End": "93.7"
    },
    {
        "lineNo": 16,
        "lineEn": "Anna:  Oh? A problem, bbbbut…",
        "linePl": "Anna: Oh? Problem, bbbbut ...\r",
        "mp3Start": "93.7",
        "mp3End": "97.2"
    },
    {
        "lineNo": 17,
        "lineEn": "Narrator: Let me teach you some phrases you might need to explain that there's been a mistake:",
        "linePl": "Narrator: Pozwolę sobie nauczyć niektórych zwrotów, które mogą być konieczne, aby wyjaśnić, że popełniono błąd:\r",
        "mp3Start": "97.2",
        "mp3End": "101.7"
    },
    {
        "lineNo": 18,
        "lineEn": "I think there's been a misunderstanding.",
        "linePl": "Myślę, że było nieporozumienie.\r",
        "mp3Start": "101.7",
        "mp3End": "105.0"
    },
    {
        "lineNo": 19,
        "lineEn": "Or: There's been a bit of a mix-up.",
        "linePl": "Lub:\r Było trochę zamieszania.\r",
        "mp3Start": "104.7",
        "mp3End": "107.4"
    },
    {
        "lineNo": 20,
        "lineEn": "Anna:  But what misunderstanding? What mix-up?",
        "linePl": "Anna: Ale co za nieporozumienie? Jakie mieszanie?\r",
        "mp3Start": "107.4",
        "mp3End": "111.5"
    },
    {
        "lineNo": 21,
        "lineEn": "Narrator: You could also use: Let me explain what happened...",
        "linePl": "Narrator: Można również użyć:\r Pozwól mi wyjaśnić, co się stało ...\r",
        "mp3Start": "111.5",
        "mp3End": "114.9"
    },
    {
        "lineNo": 22,
        "lineEn": "Paul:  Ah, good afternoon everyone. All:  Hello.",
        "linePl": "Paul: Ach, dzień dobry po południu wszyscy.\n Wszyscy: cześć.\n",
        "mp3Start": "116.9",
        "mp3End": "121.4"
    },
    {
        "lineNo": 23,
        "lineEn": "Paul:  Tom, this is an excellent piece of work!",
        "linePl": "Paul: Tom, to świetna robota!\r",
        "mp3Start": "121.4",
        "mp3End": "124.7"
    },
    {
        "lineNo": 24,
        "lineEn": "Tom:  Sorry?",
        "linePl": "Tom: Przepraszam?\r",
        "mp3Start": "124.7",
        "mp3End": "126"
    },
    {
        "lineNo": 25,
        "lineEn": "Paul:  These are by far the best ideas you've ever had.",
        "linePl": "Paul: Są zdecydowanie najlepsze pomysły, jakie kiedykolwiek jadłeś.\r",
        "mp3Start": "126",
        "mp3End": "130.2"
    },
    {
        "lineNo": 26,
        "lineEn": "Tom:  I don't understand.",
        "linePl": "Tom: Nie rozumiem.\r",
        "mp3Start": "130.2",
        "mp3End": "132.2"
    },
    {
        "lineNo": 27,
        "lineEn": "Paul:  Our stock management system!",
        "linePl": "Paul: Nasz system zarządzania zapasami!\r",
        "mp3Start": "132.2",
        "mp3End": "134.3"
    },
    {
        "lineNo": 28,
        "lineEn": "Tom:  Can I see? … Oh, that's not mine. Paul:  Eh?",
        "linePl": "Tom: Czy mogę zobaczyć? ... Oh, to nie moje.\r Paul: Eh?\r",
        "mp3Start": "134.3",
        "mp3End": "139.6"
    },
    {
        "lineNo": 29,
        "lineEn": "Anna:  I think there's been a misunderstanding. I did it.",
        "linePl": "Anna: Myślę, że było nieporozumienie. Ja to zrobiłem.\r",
        "mp3Start": "139.8",
        "mp3End": "143.7"
    },
    {
        "lineNo": 30,
        "lineEn": "Paul+Tom:  You?",
        "linePl": "Paul + Tom: Ty?\r",
        "mp3Start": "143.7",
        "mp3End": "145.3"
    },
    {
        "lineNo": 31,
        "lineEn": "Anna:  I got your note Paul, here.",
        "linePl": "Anna: Dostałem twoją notatkę Paul, tutaj.\r",
        "mp3Start": "145.3",
        "mp3End": "148.5"
    },
    {
        "lineNo": 32,
        "lineEn": "Paul:  No, no, that note was for Tom.",
        "linePl": "Paul: Nie, nie, ta notatka była dla Tom.\r",
        "mp3Start": "148.5",
        "mp3End": "151.4"
    },
    {
        "lineNo": 33,
        "lineEn": "Anna:  Oh, then there's been a bit of a mix up.",
        "linePl": "Anna: Oh, wtedy było trochę zamieszania.\r",
        "mp3Start": "151.4",
        "mp3End": "155.2"
    },
    {
        "lineNo": 34,
        "lineEn": "Tom:  Did you take that note from my desk?",
        "linePl": "Tom: Czy wziąłeś tę notatkę z mojego biurka?\r",
        "mp3Start": "155.2",
        "mp3End": "157.3"
    },
    {
        "lineNo": 35,
        "lineEn": "Anna:  No, no!",
        "linePl": "Anna: Nie, nie!\r",
        "mp3Start": "157.9",
        "mp3End": "158.3"
    },
    {
        "lineNo": 36,
        "lineEn": "Tom:  I suppose you threw my pear salesman certificate on the floor at the same time too!",
        "linePl": "Tom: Przypuszczam, że w tym samym czasie zrzuciłaś certyfikat mojej sprzedaży gruszki na podłogę!\r",
        "mp3Start": "158.5",
        "mp3End": "163.0"
    },
    {
        "lineNo": 37,
        "lineEn": "Anna: I didn’t! Let me explain. The wind must have blown the note for Tom under my desk.",
        "linePl": "Anna: Nie! Pozwól mi wyjaśnić. Wiatr podmuchał notatkę dla Toma pod biurkiem.\r",
        "mp3Start": "163.2",
        "mp3End": "169.9"
    },
    {
        "lineNo": 38,
        "lineEn": "Denise: Tom left the window open overnight. Our papers were blown all over the place.",
        "linePl": "Denise: Tom zostawił okno otwarte przez noc. Nasze dokumenty zostały rozdmuchiwane w całym miejscu.\r",
        "mp3Start": "170",
        "mp3End": "175.9"
    },
    {
        "lineNo": 39,
        "lineEn": "Paul:  I see, well, golly gosh. In that case, well done, Anna! Excellent work, even though you weren't meant to do it. And Tom, your ideas are still welcome of course. Thanks.",
        "linePl": "Paul: Widzę, dobrze, golly gosh. W takim przypadku, dobrze, Anna! Doskonała praca, nawet jeśli nie miałeś tego robić. I Tom, twoje pomysły są oczywiście mile widziane. Dzięki.\r",
        "mp3Start": "176.1",
        "mp3End": "189.0"
    },
    {
        "lineNo": 40,
        "lineEn": "Anna:  Sorry Tom.",
        "linePl": "Anna: Przepraszam Tom.\r",
        "mp3Start": "189.7",
        "mp3End": "190.9"
    },
    {
        "lineNo": 41,
        "lineEn": "Tom:  What? Oh, I'm not bothered. I've still got some great ideas in my head anyway.",
        "linePl": "Tom: Co? Nie martw się. W każdym razie wciąż mam w głowie wspaniałe pomysły.\r",
        "mp3Start": "190.9",
        "mp3End": "196.0"
    },
    {
        "lineNo": 42,
        "lineEn": "Narrator: Yeah, right! Let's leave Tom to get on with his 'great ideas' and listen again those phrases Anna used to explain the misunderstanding:",
        "linePl": "Narrator: Yeah, dobrze! Zostawmy Tom'owi, aby kontynuować swoje \"wspaniałe pomysły\" i ponownie posłuchajmy tych zwrotów, które Anna wytłumaczyła nieporozumienie:\n",
        "mp3Start": "197.2",
        "mp3End": "206.5"
    },
    {
        "lineNo": 43,
        "lineEn": "I think there's been a misunderstanding.",
        "linePl": "Myślę, że było nieporozumienie.\r",
        "mp3Start": "206.5",
        "mp3End": "209.8"
    },
    {
        "lineNo": 44,
        "lineEn": "There's been a bit of a mix-up.",
        "linePl": "Było trochę zamieszania.\r",
        "mp3Start": "209.8",
        "mp3End": "211.7"
    },
    {
        "lineNo": 45,
        "lineEn": "Let me explain what happened.",
        "linePl": "Pozwólcie mi wyjaśnić, co się stało.\r",
        "mp3Start": "211.7",
        "mp3End": "214.0"
    },
    {
        "lineNo": 46,
        "lineEn": "Well, the mix-up gave Anna a chance to shine – Paul certainly seemed impressed with her work. Maybe it will bring her new opportunities. Until next time, bye!",
        "linePl": "Cóż, mieszanka dała Anna szansę na blask - Paul chyba wydawał się pod wrażeniem jej pracy. Może przyniesie jej nowe możliwości. Do następnego razu, do widzenia!\r",
        "mp3Start": "215.0",
        "mp3End": "224.5"
    },
    {
        "lineNo": 47,
        "lineEn": " Listening Challenge",
        "linePl": "• Słuchanie Wyzwanie\r",
        "mp3Start": "",
        "mp3End": ""
    },
    {
        "lineNo": 48,
        "lineEn": "Tom found one of his certificates on the floor. What was it for?",
        "linePl": "Tom znalazł jedno ze swoich certyfikatów na podłodze. Co to było?\r",
        "mp3Start": "",
        "mp3End": ""
    },
    {
        "lineNo": 49,
        "lineEn": "Answer: Plastic Pear Salesman of the Year",
        "linePl": "Odpowiedź: Plastikowa Sprzedaż Pear of the Year ",
        "mp3Start": "",
        "mp3End": ""
    }
]